civismlext/__init__.py
civismlext/hyperband.py
civismlext/nonnegative.py
civismlext/preprocessing.py
civismlext/stacking.py
civismlext/test/__init__.py
civismlext/test/test_hyperband.py
civismlext/test/test_nonnegative.py
civismlext/test/test_preprocessing.py
civismlext/test/test_stacking.py
civisml_extensions-0.3.1.dist-info/LICENSE.md
civisml_extensions-0.3.1.dist-info/METADATA
civisml_extensions-0.3.1.dist-info/WHEEL
civisml_extensions-0.3.1.dist-info/top_level.txt
civisml_extensions-0.3.1.dist-info/RECORD
