Metadata-Version: 2.1
Name: civisml-extensions
Version: 0.3.1
Summary: scikit-learn-compatible estimators from Civis Analytics
Home-page: https://www.civisanalytics.com
Author: Civis Analytics
Author-email: opensource@civisanalytics.com
License: BSD-3
Platform: UNKNOWN
Classifier: Programming Language :: Python
Classifier: Programming Language :: Python :: 3
Classifier: Programming Language :: Python :: 3.6
Classifier: Programming Language :: Python :: 3.7
Classifier: Programming Language :: Python :: 3.8
Classifier: Programming Language :: Python :: 3 :: Only
Requires-Python: >=3.6
Requires-Dist: joblib (>=0.14.0)
Requires-Dist: numpy (<2.0,>=1.12)
Requires-Dist: pandas (>=0.25)
Requires-Dist: scikit-learn (<0.24.0,>=0.18.1)
Requires-Dist: scipy (<2.0,>=0.14)
Requires-Dist: six (~=1.10)
